btIntegration
