Metadata-Version: 2.1
Name: btnexus-integration-python
Version: 0.3.25
Summary: Provides utilities for btNexus Integrations in python
Home-page: https://btnexus.ai
Author: Blackout Technologies
Author-email: dev@blackout.ai
License: UNKNOWN
Platform: UNKNOWN
Classifier: License :: OSI Approved :: GNU Lesser General Public License v3 or later (LGPLv3+)
Classifier: Programming Language :: Python :: 3.6
Classifier: Programming Language :: Python :: 3.7
